{
    "identityPoolName": "yoyolunchboxb0fb0c31_identitypool_b0fb0c31",
    "allowUnauthenticatedIdentities": false,
    "resourceNameTruncated": "yoyolub0fb0c31",
    "userPoolName": "yoyolunchboxb0fb0c31_userpool_b0fb0c31",
    "autoVerifiedAttributes": [
        "email"
    ],
    "mfaConfiguration": "OFF",
    "mfaTypes": [
        "SMS Text Message"
    ],
    "smsAuthenticationMessage": "Your authentication code is {####}",
    "smsVerificationMessage": "Your verification code is {####}",
    "emailVerificationSubject": "Your verification code",
    "emailVerificationMessage": "Your verification code is {####}",
    "defaultPasswordPolicy": false,
    "passwordPolicyMinLength": 8,
    "passwordPolicyCharacters": [],
    "requiredAttributes": [
        "phone_number"
    ],
    "aliasAttributes": [
        "email",
        "preferred_username",
        "phone_number"
    ],
    "userpoolClientGenerateSecret": false,
    "userpoolClientRefreshTokenValidity": 30,
    "userpoolClientWriteAttributes": [
        "email"
    ],
    "userpoolClientReadAttributes": [
        "email"
    ],
    "userpoolClientLambdaRole": "yoyolub0fb0c31_userpoolclient_lambda_role",
    "userpoolClientSetAttributes": false,
    "sharedId": "b0fb0c31",
    "resourceName": "yoyolunchboxb0fb0c31",
    "authSelections": "identityPoolAndUserPool",
    "authRoleArn": {
        "Fn::GetAtt": [
            "AuthRole",
            "Arn"
        ]
    },
    "unauthRoleArn": {
        "Fn::GetAtt": [
            "UnauthRole",
            "Arn"
        ]
    },
    "useDefault": "default",
    "triggers": "{}",
    "userPoolGroupList": [],
    "serviceName": "Cognito",
    "usernameCaseSensitive": false,
    "parentStack": {
        "Ref": "AWS::StackId"
    },
    "breakCircularDependency": true,
    "permissions": [],
    "dependsOn": []
}